libcrypt/__init__.py
libcrypt-1.2.0.dist-info/METADATA
libcrypt-1.2.0.dist-info/WHEEL
libcrypt-1.2.0.dist-info/top_level.txt
libcrypt-1.2.0.dist-info/RECORD
