Metadata-Version: 2.1
Name: libcrypt
Version: 1.2.0
Summary: Package that helps with other cryptography related python packages
Home-page: UNKNOWN
Author: NHJonas
Author-email: NHJonas@gmail.com
License: UNKNOWN
Keywords: python
Platform: UNKNOWN
Classifier: Operating System :: Microsoft :: Windows
